{"_type":"export","__export_format":4,"__export_date":"2019-11-24T21:46:47.139Z","__export_source":"insomnia.desktop.app:v7.0.3","resources":[{"_id":"req_4e6c82b782fa4d4b9dfc3fcb17255b2a","authentication":{"token":"","type":"bearer"},"body":{"mimeType":"application/json","text":"{\n\t\"email\":\"admin@gympoint.com\",\n\t\"password\":\"123456\"\n}"},"created":1568304729882,"description":"","headers":[{"id":"pair_8dd8a4ad91134496b78f48d25cda774e","name":"Content-Type","value":"application/json"}],"isPrivate":false,"metaSortKey":-1567566246568,"method":"POST","modified":1571928014819,"name":"Create","parameters":[],"parentId":"fld_1f09288525e54f65a94e8dd4116e893b","settingDisableRenderRequestBody":false,"settingEncodeUrl":true,"settingRebuildPath":true,"settingSendCookies":true,"settingStoreCookies":true,"url":"{{ base_url  }}/sessions","_type":"request"},{"_id":"fld_1f09288525e54f65a94e8dd4116e893b","created":1568304727647,"description":"","environment":{},"environmentPropertyOrder":null,"metaSortKey":-1568304727650,"modified":1568304727647,"name":"Sessions","parentId":"wrk_b954d35758dd4a85990f0ca27e9e4033","_type":"request_group"},{"_id":"wrk_b954d35758dd4a85990f0ca27e9e4033","created":1568041313285,"description":"","modified":1571240988381,"name":"Gympoint","parentId":null,"_type":"workspace"},{"_id":"req_1d4efab0e873455fa0c47ec92de568b7","authentication":{"prefix":"","token":"{{ token  }}","type":"bearer"},"body":{"mimeType":"application/json","text":"{\n\t\"name\":\"karma5\",\n\t\"email\":\"karma@gmail.com\",\n\t\"age\":20,\n\t\"weight\":55,\n\t\"height\":1.2334444\n}"},"created":1571664199003,"description":"","headers":[{"id":"pair_39a21d09fc7a4415b468162a885cf655","name":"Content-Type","value":"application/json"}],"isPrivate":false,"metaSortKey":-1571664199004,"method":"PUT","modified":1574622446560,"name":"Update Student","parameters":[],"parentId":"fld_1e39b568f4124d9ea4984ceb466f46b7","settingDisableRenderRequestBody":false,"settingEncodeUrl":true,"settingRebuildPath":true,"settingSendCookies":true,"settingStoreCookies":true,"url":"{{ base_url  }}/students/3","_type":"request"},{"_id":"fld_1e39b568f4124d9ea4984ceb466f46b7","created":1571331550514,"description":"","environment":{},"environmentPropertyOrder":null,"metaSortKey":-1568041436976,"modified":1571331589746,"name":"Students","parentId":"wrk_b954d35758dd4a85990f0ca27e9e4033","_type":"request_group"},{"_id":"req_e9bc2f6283294961b3533c810d0bc838","authentication":{"token":"{{ token  }}","type":"bearer"},"body":{"mimeType":"application/json","text":"{\n\t\"name\":\"master\",\n\t\"email\":\"master@gmail.com\",\n\t\"age\":22,\n\t\"weight\":69.235333333,\n\t\"height\":1.90444444444\n}"},"created":1571331611900,"description":"","headers":[{"id":"pair_c22c3dc340ec4f3b84da04e58c6aaa7c","name":"Content-Type","value":"application/json"}],"isPrivate":false,"metaSortKey":-1571331611900,"method":"POST","modified":1573021838460,"name":"Create Students","parameters":[],"parentId":"fld_1e39b568f4124d9ea4984ceb466f46b7","settingDisableRenderRequestBody":false,"settingEncodeUrl":true,"settingRebuildPath":true,"settingSendCookies":true,"settingStoreCookies":true,"url":"{{ base_url  }}/students","_type":"request"},{"_id":"req_bfcff940edaf42a1be1069db7459cb4f","authentication":{"token":"{{ token  }}","type":"bearer"},"body":{"mimeType":"application/json","text":"{\n\t\"title\":\"Master\",\n\t\"duration\":\"16\",\n\t\"monthly_price\":\"60\"\n}"},"created":1571936249296,"description":"","headers":[{"id":"pair_415d55210235406880284e9ad68b7d86","name":"Content-Type","value":"application/json"},{"id":"pair_028e83677d844b19b3501eeb63b000c8","name":"","value":""}],"isPrivate":false,"metaSortKey":-1571936249296,"method":"POST","modified":1574610568085,"name":"Create Plans","parameters":[],"parentId":"fld_9e2f6ac606524fe98480698aa64af8ae","settingDisableRenderRequestBody":false,"settingEncodeUrl":true,"settingRebuildPath":true,"settingSendCookies":true,"settingStoreCookies":true,"url":"{{ base_url  }}/plans","_type":"request"},{"_id":"fld_9e2f6ac606524fe98480698aa64af8ae","created":1571936230568,"description":"","environment":{},"environmentPropertyOrder":null,"metaSortKey":-1568041436926,"modified":1571936234384,"name":"Plans","parentId":"wrk_b954d35758dd4a85990f0ca27e9e4033","_type":"request_group"},{"_id":"req_38cab7e4a00c41ba8a35775e8a10382b","authentication":{"token":"{{ token  }}","type":"bearer"},"body":{"mimeType":"application/json","text":"{\n\t\"title\":\"Start\",\n\t\"duration\":\"1\",\n\t\"monthly_price\":\"130\"\n}"},"created":1572405386082,"description":"","headers":[{"id":"pair_415d55210235406880284e9ad68b7d86","name":"Content-Type","value":"application/json"},{"id":"pair_028e83677d844b19b3501eeb63b000c8","name":"","value":""}],"isPrivate":false,"metaSortKey":-1571800224150,"method":"PUT","modified":1573012464576,"name":"Update Plans","parameters":[],"parentId":"fld_9e2f6ac606524fe98480698aa64af8ae","settingDisableRenderRequestBody":false,"settingEncodeUrl":true,"settingRebuildPath":true,"settingSendCookies":true,"settingStoreCookies":true,"url":"{{ base_url  }}/plans/5","_type":"request"},{"_id":"req_71ffea8ff227440399953403b4f41ae2","authentication":{"token":"{{ token  }}","type":"bearer"},"body":{},"created":1572406172589,"description":"","headers":[{"id":"pair_028e83677d844b19b3501eeb63b000c8","name":"","value":""}],"isPrivate":false,"metaSortKey":-1571732211577,"method":"DELETE","modified":1573012446571,"name":"Delete Plans","parameters":[],"parentId":"fld_9e2f6ac606524fe98480698aa64af8ae","settingDisableRenderRequestBody":false,"settingEncodeUrl":true,"settingRebuildPath":true,"settingSendCookies":true,"settingStoreCookies":true,"url":"{{ base_url  }}/plans/5","_type":"request"},{"_id":"req_c5d73d94f36e459198399ac3b91b032e","authentication":{"token":"{{ token  }}","type":"bearer"},"body":{},"created":1572408370840,"description":"","headers":[{"id":"pair_028e83677d844b19b3501eeb63b000c8","name":"","value":""}],"isPrivate":false,"metaSortKey":-1571732211527,"method":"GET","modified":1572408395339,"name":"List Plans","parameters":[],"parentId":"fld_9e2f6ac606524fe98480698aa64af8ae","settingDisableRenderRequestBody":false,"settingEncodeUrl":true,"settingRebuildPath":true,"settingSendCookies":true,"settingStoreCookies":true,"url":"{{ base_url  }}/plans","_type":"request"},{"_id":"req_ac6487046fd846efa9a7d09d910c0da0","authentication":{"token":"{{ token  }}","type":"bearer"},"body":{},"created":1574628700728,"description":"","headers":[],"isPrivate":false,"metaSortKey":-1574628700728,"method":"GET","modified":1574629792155,"name":"List Enrollment","parameters":[{"id":"pair_9e469675ef9441a083548c1eb4c2cdfe","name":"page","value":"1"}],"parentId":"fld_bfc9fef1509744c5a25b535fe2f8b1c7","settingDisableRenderRequestBody":false,"settingEncodeUrl":true,"settingRebuildPath":true,"settingSendCookies":true,"settingStoreCookies":true,"url":"{{ base_url  }}/enrollments","_type":"request"},{"_id":"fld_bfc9fef1509744c5a25b535fe2f8b1c7","created":1573142127310,"description":"","environment":{},"environmentPropertyOrder":null,"metaSortKey":-1568041436876,"modified":1573142143374,"name":"Enrollment","parentId":"wrk_b954d35758dd4a85990f0ca27e9e4033","_type":"request_group"},{"_id":"req_8cdf104d079c4c88bd8ed571774649ee","authentication":{"token":"{{ token  }}","type":"bearer"},"body":{},"created":1574630161517,"description":"","headers":[],"isPrivate":false,"metaSortKey":-1573282475012,"method":"GET","modified":1574630287355,"name":"List Enrollment UNIQUE","parameters":[],"parentId":"fld_bfc9fef1509744c5a25b535fe2f8b1c7","settingDisableRenderRequestBody":false,"settingEncodeUrl":true,"settingRebuildPath":true,"settingSendCookies":true,"settingStoreCookies":true,"url":"{{ base_url  }}/enrollments/2","_type":"request"},{"_id":"req_2f4f48f54bda44d480faf3090ccaba9a","authentication":{"token":"{{ token  }}","type":"bearer"},"body":{"mimeType":"application/json","text":"\n\t{\n  \"student_id\": 2,\n  \"plan_id\": 4,\n  \"start_date\": \"2019-11-24\"\n}\n"},"created":1573142127344,"description":"","headers":[{"id":"pair_953bc549ddd64562a218e06feb211f7d","name":"Content-Type","value":"application/json"}],"isPrivate":false,"metaSortKey":-1571664199054,"method":"POST","modified":1574625413028,"name":"Create Enrollment","parameters":[],"parentId":"fld_bfc9fef1509744c5a25b535fe2f8b1c7","settingDisableRenderRequestBody":false,"settingEncodeUrl":true,"settingRebuildPath":true,"settingSendCookies":true,"settingStoreCookies":true,"url":"{{ base_url  }}/enrollments","_type":"request"},{"_id":"req_744f0436462a464f96f2d64e311c81c5","authentication":{"prefix":"","token":"{{ token  }}","type":"bearer"},"body":{"mimeType":"application/json","text":"\t{\n  \"plan_id\": 4,\n  \"start_date\": \"2019-11-24\"\n}"},"created":1573142127370,"description":"","headers":[{"id":"pair_39a21d09fc7a4415b468162a885cf655","name":"Content-Type","value":"application/json"}],"isPrivate":false,"metaSortKey":-1571664199004,"method":"PUT","modified":1574627766600,"name":"Update Enrollment","parameters":[],"parentId":"fld_bfc9fef1509744c5a25b535fe2f8b1c7","settingDisableRenderRequestBody":false,"settingEncodeUrl":true,"settingRebuildPath":true,"settingSendCookies":true,"settingStoreCookies":true,"url":"{{ base_url  }}/enrollments/6","_type":"request"},{"_id":"req_8e72e6f1901a42ddb55b35879fd699f2","authentication":{"token":"{{ token  }}","type":"bearer"},"body":{},"created":1574630599733,"description":"","headers":[],"isPrivate":false,"metaSortKey":-1571664198954,"method":"DELETE","modified":1574630856090,"name":"Delete Enrollment","parameters":[{"id":"pair_9e469675ef9441a083548c1eb4c2cdfe","name":"","value":""}],"parentId":"fld_bfc9fef1509744c5a25b535fe2f8b1c7","settingDisableRenderRequestBody":false,"settingEncodeUrl":true,"settingRebuildPath":true,"settingSendCookies":true,"settingStoreCookies":true,"url":"{{ base_url  }}/enrollments/31","_type":"request"},{"_id":"env_eb9557c184771fb28b9e94d4d04ab71421f7554b","color":null,"created":1568041313520,"data":{"base_url":"http://localhost:3333","token":"eyJhbGciOiJIUzI1NiIsInR5cCI6IkpXVCJ9.eyJpZCI6MTIsImlhdCI6MTU3NDYwODk2NywiZXhwIjoxNTc1MjEzNzY3fQ.XPvag3PmqRFLWMRWDt9e0E7t0QiZRv4gi0UGYZMh6k8"},"dataPropertyOrder":{"&":["base_url","token"]},"isPrivate":false,"metaSortKey":1568041313520,"modified":1574608979160,"name":"Base Environment","parentId":"wrk_b954d35758dd4a85990f0ca27e9e4033","_type":"environment"},{"_id":"jar_eb9557c184771fb28b9e94d4d04ab71421f7554b","cookies":[],"created":1568041313532,"modified":1568041313532,"name":"Default Jar","parentId":"wrk_b954d35758dd4a85990f0ca27e9e4033","_type":"cookie_jar"}]}